MANIFEST.in
README.rst
setup.py
orcid/__init__.py
orcid/constants.py
orcid/exceptions.py
orcid/rest.py
orcid/utils.py
orcid_python.egg-info/PKG-INFO
orcid_python.egg-info/SOURCES.txt
orcid_python.egg-info/dependency_links.txt
orcid_python.egg-info/requires.txt
orcid_python.egg-info/top_level.txt