Metadata-Version: 1.1
Name: orcid-python
Version: 0.1
Summary: A simple wrapper around the ORCID.org API.
Home-page: https://github.com/scholrly/orcid-python
Author: Matt Luongo
Author-email: mhluongo@gmail.com
License: MIT
Platform: UNKNOWN
Classifier: Development Status :: 3 - Alpha
Classifier: License :: OSI Approved :: MIT License
